mcp_task_flow_pro/__init__.py
mcp_task_flow_pro/server.py
mcp_task_flow_pro-0.1.0.dist-info/METADATA
mcp_task_flow_pro-0.1.0.dist-info/WHEEL
mcp_task_flow_pro-0.1.0.dist-info/entry_points.txt
mcp_task_flow_pro-0.1.0.dist-info/RECORD
