Metadata-Version: 2.4
Name: mcp-task-flow-pro
Version: 0.1.0
Summary: A simple task management MCP for adding, completing, and tracking tasks
Requires-Python: >=3.10
Requires-Dist: fastmcp>=2.0.0
